maverick_coref_de-1.0.6.dist-info/licenses/LICENSE.txt
maverick_de/__init__.py
maverick_de/evaluate.py
maverick_de/train.py
maverick_de/common/constants.py
maverick_de/common/metrics.py
maverick_de/common/util.py
maverick_de/data/dataloader.py
maverick_de/data/datasets.py
maverick_de/data/pl_data_modules.py
maverick_de/models/__init__.py
maverick_de/models/maverick_model.py
maverick_de/models/model_incr.py
maverick_de/models/model_mes.py
maverick_de/models/model_s2e.py
maverick_de/models/pl_modules.py
maverick_de/utils/__init__.py
maverick_de/utils/loggingl.py
maverick_coref_de-1.0.6.dist-info/METADATA
maverick_coref_de-1.0.6.dist-info/WHEEL
maverick_coref_de-1.0.6.dist-info/top_level.txt
maverick_coref_de-1.0.6.dist-info/RECORD
