Metadata-Version: 2.4
Name: maverick-coref-de
Version: 1.0.6
Summary: co-reference resolution for German using the Maverick system
Author: Fynn Petersen-Frey, Giuliano Martinelli
License-Expression: CC-BY-NC-SA-4.0
Project-URL: Repository, https://github.com/uhh-lt/maverick-coref-de.git
Requires-Python: >=3.10
License-File: LICENSE.txt
Requires-Dist: transformers[torch]==4.49
Requires-Dist: pytorch-lightning
Requires-Dist: pandas
Requires-Dist: hydra-core
Requires-Dist: jsonlines
Requires-Dist: nltk
Requires-Dist: torch>=2.0
Requires-Dist: sentencepiece
Requires-Dist: scipy
Requires-Dist: numpy
Requires-Dist: protobuf
Requires-Dist: spacy
Requires-Dist: huggingface-hub
Requires-Dist: flash-attn
Requires-Dist: tqdm
Dynamic: license-file
